stock_pandas/__init__.py
stock_pandas/backend.py
stock_pandas/commands/__init__.py
stock_pandas/commands/base.py
stock_pandas/commands/common.py
stock_pandas/commands/over_bought_or_sold.py
stock_pandas/commands/support_and_resistance.py
stock_pandas/commands/tools.py
stock_pandas/commands/trend_following.py
stock_pandas/common.py
stock_pandas/dataframe.py
stock_pandas/directive/__init__.py
stock_pandas/directive/cache.py
stock_pandas/directive/command.py
stock_pandas/directive/node.py
stock_pandas/directive/operator.py
stock_pandas/directive/parse.py
stock_pandas/directive/parser.py
stock_pandas/directive/syntax.ebnf
stock_pandas/directive/tokenizer.py
stock_pandas/directive/types.py
stock_pandas/exceptions.py
stock_pandas/math/__init__.py
stock_pandas/math/_lib.pyi
stock_pandas/math/_lib.pyx
stock_pandas/math/ma.py
stock_pandas/meta/__init__.py
stock_pandas/meta/cumulator.py
stock_pandas/meta/date.py
stock_pandas/meta/time_frame.py
stock_pandas/meta/utils.py
stock_pandas/properties.py
stock_pandas/py.typed
stock_pandas-5.3.2.dist-info/METADATA
stock_pandas-5.3.2.dist-info/WHEEL
stock_pandas-5.3.2.dist-info/licenses/LICENSE
stock_pandas_rs/__init__.py
stock_pandas_rs/stock_pandas_rs.cpython-312-darwin.so
stock_pandas-5.3.2.dist-info/RECORD
