Metadata-Version: 2.4
Name: stock-pandas
Version: 5.3.2
Classifier: Programming Language :: Python
Classifier: Programming Language :: Python :: 3.11
Classifier: Programming Language :: Python :: 3.12
Classifier: Programming Language :: Python :: 3.13
Classifier: Programming Language :: Python :: 3.14
Classifier: Programming Language :: Rust
Classifier: Programming Language :: Python :: Implementation :: CPython
Classifier: Natural Language :: English
Classifier: Intended Audience :: Developers
Classifier: Intended Audience :: Financial and Insurance Industry
Classifier: Operating System :: OS Independent
Classifier: Development Status :: 4 - Beta
Classifier: Topic :: Utilities
Requires-Dist: numpy>=2.0.0
Requires-Dist: pandas>=1.0.0
Requires-Dist: coverage ; extra == 'dev'
Requires-Dist: ruff ; extra == 'dev'
Requires-Dist: pytest ; extra == 'dev'
Requires-Dist: pytest-cov ; extra == 'dev'
Requires-Dist: pytest-benchmark ; extra == 'dev'
Requires-Dist: twine ; extra == 'dev'
Requires-Dist: numpy>=2.0.0 ; extra == 'dev'
Requires-Dist: mypy ; extra == 'dev'
Requires-Dist: maturin>=1.4 ; extra == 'dev'
Provides-Extra: dev
License-File: LICENSE
Summary: The production-ready subclass of `pandas.DataFrame` to support stock statistics and indicators.
Home-Page: https://github.com/kaelzhang/stock-pandas
Author-email: Kael Zhang <i+pypi@kael.me>
License-Expression: MIT
Requires-Python: >=3.10
Project-URL: Homepage, https://github.com/kaelzhang/stock-pandas
